doc2graph/__init__.py
doc2graph/src/__init__.py
doc2graph/src/inference.py
doc2graph/src/main.py
doc2graph/src/paths.py
doc2graph/src/utils.py
doc2graph/src/data/__init__.py
doc2graph/src/data/clone_utils.py
doc2graph/src/data/dataloader.py
doc2graph/src/data/download.py
doc2graph/src/data/feature_builder.py
doc2graph/src/data/find_items.py
doc2graph/src/data/graph_builder.py
doc2graph/src/data/graph_utils copy.py
doc2graph/src/data/graph_utils.py
doc2graph/src/data/image_utils.py
doc2graph/src/data/preprocessing.py
doc2graph/src/data/utils.py
doc2graph/src/models/__init__.py
doc2graph/src/models/gatconv.py
doc2graph/src/models/gatv2conv.py
doc2graph/src/models/gatv2conv_bk.py
doc2graph/src/models/graphs.py
doc2graph/src/models/utils.py
doc2graph/src/models/unet/__init__.py
doc2graph/src/models/unet/decoder.py
doc2graph/src/models/unet/model.py
doc2graph/src/training/__init__.py
doc2graph/src/training/funsd.py
doc2graph/src/training/pau.py
doc2graph/src/training/remittance.py
doc2graph/src/training/utils.py
doc2graph-3.3.9.dist-info/LICENCE
doc2graph-3.3.9.dist-info/METADATA
doc2graph-3.3.9.dist-info/WHEEL
doc2graph-3.3.9.dist-info/top_level.txt
doc2graph-3.3.9.dist-info/RECORD
